server/__init__.py
server/server.py
server/common/__init__.py
server/common/descriptrs.py
server/common/errors.py
server/common/log_decor.py
server/common/metaclasses.py
server/common/utils.py
server/common/variables.py
server/doc/__init__.py
server/doc/source/__init__.py
server/doc/source/conf.py
server/logs/__init__.py
server/logs/config_server_log.py
server/server/__init__.py
server/server/add_user.py
server/server/config_window.py
server/server/core.py
server/server/main_window.py
server/server/remove_user.py
server/server/server_database.py
server/server/stat_window.py
server/unit_tests/__init__.py
server/unit_tests/test_server.py
server/unit_tests/test_utils.py
ICQ_server-0.1.0.dist-info/METADATA
ICQ_server-0.1.0.dist-info/WHEEL
ICQ_server-0.1.0.dist-info/top_level.txt
ICQ_server-0.1.0.dist-info/RECORD
