Metadata-Version: 2.1
Name: ICQ-server
Version: 0.1.0
Summary: ICQ_server
Home-page: UNKNOWN
Author: Evseev Yurii
Author-email: mousedrw@ya.ru
License: UNKNOWN
Platform: UNKNOWN
Requires-Dist: PyQt5
Requires-Dist: sqlalchemy
Requires-Dist: pycryptodome
Requires-Dist: pycryptodomex
